widgetastic_patternfly4/__init__.py
widgetastic_patternfly4/alert.py
widgetastic_patternfly4/breadcrumb.py
widgetastic_patternfly4/bulletchart.py
widgetastic_patternfly4/button.py
widgetastic_patternfly4/calendarmonth.py
widgetastic_patternfly4/card.py
widgetastic_patternfly4/chipgroup.py
widgetastic_patternfly4/clipboardcopy.py
widgetastic_patternfly4/contextselector.py
widgetastic_patternfly4/descriptionlist.py
widgetastic_patternfly4/donutchart.py
widgetastic_patternfly4/drawer.py
widgetastic_patternfly4/dropdown.py
widgetastic_patternfly4/duallistselector.py
widgetastic_patternfly4/formselect.py
widgetastic_patternfly4/linechart.py
widgetastic_patternfly4/menu.py
widgetastic_patternfly4/modal.py
widgetastic_patternfly4/navigation.py
widgetastic_patternfly4/optionsmenu.py
widgetastic_patternfly4/ouia.py
widgetastic_patternfly4/pagination.py
widgetastic_patternfly4/piechart.py
widgetastic_patternfly4/popover.py
widgetastic_patternfly4/progress.py
widgetastic_patternfly4/radio.py
widgetastic_patternfly4/select.py
widgetastic_patternfly4/slider.py
widgetastic_patternfly4/switch.py
widgetastic_patternfly4/table.py
widgetastic_patternfly4/tabs.py
widgetastic_patternfly4/title.py
widgetastic.patternfly4-1.2.7.dist-info/METADATA
widgetastic.patternfly4-1.2.7.dist-info/WHEEL
widgetastic.patternfly4-1.2.7.dist-info/licenses/LICENSE
widgetastic.patternfly4-1.2.7.dist-info/RECORD
