Metadata-Version: 2.1
Name: widgetastic.patternfly4
Version: 1.2.7
Summary: Patternfly4 widget library for Widgetastic.
Project-URL: repository, https://github.com/RedHatQE/widgetastic.patternfly4
Maintainer-email: Raoul Snyman <rsnyman@redhat.com>, Nikhil Dhandre <ndhandre@redhat.com>, Egor Shamardin <eshamard@redhat.com>
License:                                  Apache License
License-File: LICENSE
Keywords: patternfly,patternfly4,widgetastic
Classifier: Programming Language :: Python
Classifier: Programming Language :: Python :: 3
Classifier: Programming Language :: Python :: 3.8
Classifier: Programming Language :: Python :: 3.9
Classifier: Programming Language :: Python :: 3.10
Classifier: Topic :: Software Development :: Libraries :: Python Modules
Classifier: Topic :: Software Development :: Quality Assurance
Classifier: Topic :: Software Development :: Testing
Requires-Python: >=3.8
Requires-Dist: widgetastic-core>=1.0.0
Provides-Extra: dev
Requires-Dist: codecov; extra == 'dev'
Requires-Dist: pre-commit; extra == 'dev'
Requires-Dist: pytest; extra == 'dev'
Requires-Dist: pytest-cov; extra == 'dev'
Requires-Dist: pytest-xdist; extra == 'dev'
Provides-Extra: doc
Requires-Dist: sphinx; extra == 'doc'
